[{"url":"https://selcrs.nsysu.edu.tw/menu5/showoutline.asp?SYEAR=113&SEM=2&CrsDat=MATH504&Crsname=財務時間序列分析","change":null,"changeDescription":null,"multipleCompulsory":false,"department":"應數碩","id":"MATH504","grade":"0","class":"不分班","name":"財務時間序列分析\nANALYSIS OF FINANCIAL TIME SERIES","credit":"3","yearSemester":"期","compulsory":false,"restrict":20,"select":0,"selected":0,"remaining":20,"teacher":"郭美惠","room":"一3,4(理SC 4009-0) 三4(理SC 4009-0)","classTime":["34","","4","","","",""],"description":"《講授類》","tags":["金融工程學程","巨量資料分析學程"],"english":false},{"url":"https://selcrs.nsysu.edu.tw/menu5/showoutline.asp?SYEAR=113&SEM=2&CrsDat=MATH508&Crsname=統計品管","change":null,"changeDescription":null,"multipleCompulsory":false,"department":"應數碩","id":"MATH508","grade":"0","class":"不分班","name":"統計品管\nSTATISTICAL QUALITY CONTROL","credit":"3","yearSemester":"期","compulsory":false,"restrict":20,"select":0,"selected":0,"remaining":20,"teacher":"郭美惠","room":"二4(理SC 4009-1) 五3,4(理SC 4009-1)","classTime":["","4","","","34","",""],"description":"《講授類》","tags":[],"english":false},{"url":"https://selcrs.nsysu.edu.tw/menu5/showoutline.asp?SYEAR=113&SEM=2&CrsDat=MATH521&Crsname=Python與機器學習（二）","change":null,"changeDescription":null,"multipleCompulsory":false,"department":"應數碩","id":"MATH521","grade":"0","class":"不分班","name":"Python與機器學習（二）\nMACHINE LEARNING WITH PYTHON (II)","credit":"3","yearSemester":"期","compulsory":false,"restrict":30,"select":0,"selected":0,"remaining":30,"teacher":"張福春","room":"二5,6,7(理SC 4009-1)","classTime":["","567","","","","",""],"description":"《講授類》","tags":[],"english":false},{"url":"https://selcrs.nsysu.edu.tw/menu5/showoutline.asp?SYEAR=113&SEM=2&CrsDat=MATH526&Crsname=計算書報討論（一）","change":null,"changeDescription":null,"multipleCompulsory":true,"department":"應數碩","id":"MATH526","grade":"1","class":"不分班","name":"計算書報討論（一）\nSEMINAR IN SCIENTIFIC COMPUTING(I)","credit":"1","yearSemester":"期","compulsory":true,"restrict":10,"select":0,"selected":0,"remaining":10,"teacher":"李宗錂","room":"四6(理SC 4011)","classTime":["","","","6","","",""],"description":"《講授類》","tags":[],"english":false},{"url":"https://selcrs.nsysu.edu.tw/menu5/showoutline.asp?SYEAR=113&SEM=2&CrsDat=MATH532&Crsname=矩陣理論","change":null,"changeDescription":null,"multipleCompulsory":false,"department":"應數碩","id":"MATH532","grade":"0","class":"不分班","name":"矩陣理論\nMATRIX THEORY","credit":"3","yearSemester":"期","compulsory":false,"restrict":20,"select":0,"selected":0,"remaining":20,"teacher":"李宗錂","room":"三3,4(理SC 4011) 四4(理SC 4011)","classTime":["","","34","4","","",""],"description":"《講授類》","tags":[],"english":false},{"url":"https://selcrs.nsysu.edu.tw/menu5/showoutline.asp?SYEAR=113&SEM=2&CrsDat=MATH535&Crsname=無網格計算法","change":null,"changeDescription":null,"multipleCompulsory":false,"department":"應數碩","id":"MATH535","grade":"0","class":"不分班","name":"無網格計算法\nMESHLESS METHODS","credit":"3","yearSemester":"期","compulsory":false,"restrict":20,"select":0,"selected":0,"remaining":20,"teacher":"呂宗澤","room":"三6,7(理SC 4011) 四3(理SC 4011)","classTime":["","","67","3","","",""],"description":"《講授類》","tags":[],"english":false},{"url":"https://selcrs.nsysu.edu.tw/menu5/showoutline.asp?SYEAR=113&SEM=2&CrsDat=MATH551&Crsname=數學書報討論（一）","change":null,"changeDescription":null,"multipleCompulsory":true,"department":"應數碩","id":"MATH551","grade":"1","class":"不分班","name":"數學書報討論（一）\nSEMINAR IN MATHEMATICS(I)","credit":"1","yearSemester":"期","compulsory":true,"restrict":10,"select":0,"selected":0,"remaining":10,"teacher":"許柏翰","room":"四6(理SC 4013)","classTime":["","","","6","","",""],"description":"《講授類》","tags":[],"english":false},{"url":"https://selcrs.nsysu.edu.tw/menu5/showoutline.asp?SYEAR=113&SEM=2&CrsDat=MATH558&Crsname=常微分方程","change":null,"changeDescription":null,"multipleCompulsory":false,"department":"應數碩","id":"MATH558","grade":"0","class":"不分班","name":"常微分方程\nORDINARY DIFFERENTIAL EQUATIONS","credit":"3","yearSemester":"期","compulsory":false,"restrict":20,"select":0,"selected":0,"remaining":20,"teacher":"陳志漢","room":"五2,3,4(理SC 4013)","classTime":["","","","","234","",""],"description":"《講授類》","tags":[],"english":true},{"url":"https://selcrs.nsysu.edu.tw/menu5/showoutline.asp?SYEAR=113&SEM=2&CrsDat=MATH561&Crsname=拓樸學","change":null,"changeDescription":null,"multipleCompulsory":false,"department":"應數碩","id":"MATH561","grade":"0","class":"不分班","name":"拓樸學\nTOPOLOGY","credit":"3","yearSemester":"期","compulsory":false,"restrict":20,"select":0,"selected":0,"remaining":20,"teacher":"何宗軒","room":"三3,4,B(理SC 4013)","classTime":["","","34B","","","",""],"description":"《講授類》","tags":[],"english":false},{"url":"https://selcrs.nsysu.edu.tw/menu5/showoutline.asp?SYEAR=113&SEM=2&CrsDat=MATH569&Crsname=泛函分析","change":null,"changeDescription":null,"multipleCompulsory":false,"department":"應數碩","id":"MATH569","grade":"0","class":"不分班","name":"泛函分析\nFUNCTIONAL ANALYSIS","credit":"3","yearSemester":"期","compulsory":false,"restrict":20,"select":0,"selected":0,"remaining":20,"teacher":"何宗軒","room":"一5,6,7(理SC 4013)","classTime":["567","","","","","",""],"description":"《講授類》","tags":[],"english":false},{"url":"https://selcrs.nsysu.edu.tw/menu5/showoutline.asp?SYEAR=113&SEM=2&CrsDat=MATH576&Crsname=測度論","change":null,"changeDescription":null,"multipleCompulsory":false,"department":"應數碩","id":"MATH576","grade":"0","class":"不分班","name":"測度論\nMEASURE THEORY","credit":"3","yearSemester":"期","compulsory":false,"restrict":20,"select":0,"selected":0,"remaining":20,"teacher":"何宗軒","room":"四3,4,B(理SC 4013)","classTime":["","","","34B","","",""],"description":"《講授類》","tags":[],"english":false},{"url":"https://selcrs.nsysu.edu.tw/menu5/showoutline.asp?SYEAR=113&SEM=2&CrsDat=MATH586&Crsname=代數拓樸","change":null,"changeDescription":null,"multipleCompulsory":false,"department":"應數碩","id":"MATH586","grade":"0","class":"不分班","name":"代數拓樸\nALGERBRAIC TOPOLOGY","credit":"3","yearSemester":"期","compulsory":false,"restrict":20,"select":0,"selected":0,"remaining":20,"teacher":"王以晟","room":"一3,4(理SC 4013) 二B(理SC 4013)","classTime":["34","B","","","","",""],"description":"《講授類》","tags":[],"english":true},{"url":"https://selcrs.nsysu.edu.tw/menu5/showoutline.asp?SYEAR=113&SEM=2&CrsDat=MATH595&Crsname=圖形著色","change":null,"changeDescription":null,"multipleCompulsory":false,"department":"應數碩","id":"MATH595","grade":"0","class":"不分班","name":"圖形著色\nGRAPH COLORIGN","credit":"3","yearSemester":"期","compulsory":false,"restrict":20,"select":0,"selected":0,"remaining":20,"teacher":"王彩蓮","room":"二2,3,4(理SC 4011-2)","classTime":["","234","","","","",""],"description":"《講授類》","tags":[],"english":false},{"url":"https://selcrs.nsysu.edu.tw/menu5/showoutline.asp?SYEAR=113&SEM=2&CrsDat=MATH599&Crsname=Python與機器學習之理論實現","change":null,"changeDescription":null,"multipleCompulsory":false,"department":"應數碩","id":"MATH599","grade":"0","class":"不分班","name":"Python與機器學習之理論實現\nPYTHON AND MACHINE LEARNING ALGORITHMS","credit":"3","yearSemester":"期","compulsory":false,"restrict":30,"select":0,"selected":0,"remaining":30,"teacher":"林晉宏","room":"一6,7,8(理SC 4009-1)","classTime":["678","","","","","",""],"description":"《講授類》","tags":["永續能源學程","金融工程學程","製造與大數據分析微學程","跨領域智慧製造學程","人工智慧與數學學程","計算物理及人工智慧微學程"],"english":false},{"url":"https://selcrs.nsysu.edu.tw/menu5/showoutline.asp?SYEAR=113&SEM=2&CrsDat=MATH614&Crsname=統計計算專題研討（二）","change":null,"changeDescription":null,"multipleCompulsory":false,"department":"應數碩","id":"MATH614","grade":"0","class":"不分班","name":"統計計算專題研討（二）\nSEMINAR IN STUDIES IN COMPUTATIONAL STATISTICS II","credit":"3","yearSemester":"期","compulsory":false,"restrict":10,"select":0,"selected":0,"remaining":10,"teacher":"張福春","room":"三5,6,7(理SC 3002-4)","classTime":["","","567","","","",""],"description":"《研討類》","tags":[],"english":false},{"url":"https://selcrs.nsysu.edu.tw/menu5/showoutline.asp?SYEAR=113&SEM=2&CrsDat=MATH616&Crsname=時間序列專題研討（二）","change":null,"changeDescription":null,"multipleCompulsory":false,"department":"應數碩","id":"MATH616","grade":"0","class":"不分班","name":"時間序列專題研討（二）\nINDEPENDENT STUDIES IN TIME SERIES ANALYSIS II","credit":"3","yearSemester":"期","compulsory":false,"restrict":10,"select":0,"selected":0,"remaining":10,"teacher":"郭美惠","room":"三5,6,7(理SC 4027)","classTime":["","","567","","","",""],"description":"《研討類》","tags":[],"english":false},{"url":"https://selcrs.nsysu.edu.tw/menu5/showoutline.asp?SYEAR=113&SEM=2&CrsDat=MATH619&Crsname=隨機過程專題研討（一）","change":null,"changeDescription":null,"multipleCompulsory":false,"department":"應數碩","id":"MATH619","grade":"0","class":"不分班","name":"隨機過程專題研討（一）\nSEMINAR IN STOCHASTIC PROCESSES (I)","credit":"3","yearSemester":"期","compulsory":false,"restrict":10,"select":0,"selected":0,"remaining":10,"teacher":"陳美如","room":"四6,7,8(理SC 4009-0)","classTime":["","","","678","","",""],"description":"《研討類》","tags":[],"english":false},{"url":"https://selcrs.nsysu.edu.tw/menu5/showoutline.asp?SYEAR=113&SEM=2&CrsDat=MATH622&Crsname=耦合專題研討（一）","change":"異動","changeDescription":"更換時間1/6","multipleCompulsory":false,"department":"應數碩","id":"MATH622","grade":"0","class":"不分班","name":"耦合專題研討（一）\nSEMINAR IN COPULAS (I)","credit":"3","yearSemester":"期","compulsory":false,"restrict":10,"select":0,"selected":0,"remaining":10,"teacher":"施嘉翰","room":"五5,6,7(理SC 4011-2)","classTime":["","","","","567","",""],"description":"《研討類》","tags":[],"english":false},{"url":"https://selcrs.nsysu.edu.tw/menu5/showoutline.asp?SYEAR=113&SEM=2&CrsDat=MATH641&Crsname=矩陣計算專題研討","change":null,"changeDescription":null,"multipleCompulsory":false,"department":"應數碩","id":"MATH641","grade":"2","class":"不分班","name":"矩陣計算專題研討\nSEMINAR IN MATRIX COMPUTATION","credit":"3","yearSemester":"期","compulsory":false,"restrict":10,"select":0,"selected":0,"remaining":10,"teacher":"李宗錂","room":"二5,6,7(理SC 4011)","classTime":["","567","","","","",""],"description":"《研討類》","tags":[],"english":false},{"url":"https://selcrs.nsysu.edu.tw/menu5/showoutline.asp?SYEAR=113&SEM=2&CrsDat=MATH644&Crsname=影像處理專題研討","change":null,"changeDescription":null,"multipleCompulsory":false,"department":"應數碩","id":"MATH644","grade":"0","class":"不分班","name":"影像處理專題研討\nSEMINAR IN IMAGE PROCESSING","credit":"3","yearSemester":"期","compulsory":false,"restrict":10,"select":0,"selected":0,"remaining":10,"teacher":"鍾思齊","room":"三5,6,7(理SC 4009-1)","classTime":["","","567","","","",""],"description":"《研討類》","tags":[],"english":false}]