[{"url":"https://selcrs.nsysu.edu.tw/menu5/showoutline.asp?SYEAR=112&SEM=1&CrsDat=CL243&Crsname=孟子","change":null,"changeDescription":null,"multipleCompulsory":false,"department":"中文系","id":"CL243","grade":"1","class":"不分班","name":"孟子\nMENCIUS","credit":"3","yearSemester":"期","compulsory":false,"restrict":39,"select":0,"selected":35,"remaining":4,"teacher":"吳孟謙","room":"文LA 4001","classTime":["","234","","","","",""],"description":"《講授類》","tags":[],"english":false},{"url":"https://selcrs.nsysu.edu.tw/menu5/showoutline.asp?SYEAR=112&SEM=1&CrsDat=CL303&Crsname=中國思想史（一）","change":null,"changeDescription":null,"multipleCompulsory":false,"department":"中文系","id":"CL303","grade":"3","class":"不分班","name":"中國思想史（一）\nHISTORY OF CHINESE THOUGHTS(I)","credit":"3","yearSemester":"期","compulsory":true,"restrict":50,"select":0,"selected":55,"remaining":-5,"teacher":"紀志昌","room":"文LA 2004","classTime":["","567","","","","",""],"description":"《講授類》","tags":[],"english":false},{"url":"https://selcrs.nsysu.edu.tw/menu5/showoutline.asp?SYEAR=112&SEM=1&CrsDat=CL307&Crsname=詞曲選及習作（一）","change":null,"changeDescription":null,"multipleCompulsory":true,"department":"中文系","id":"CL307","grade":"3","class":"不分班","name":"詞曲選及習作（一）\nREADING IN TZ'U & CH'U POETRY(WITH EXERCISE)(I)","credit":"3","yearSemester":"期","compulsory":true,"restrict":30,"select":0,"selected":21,"remaining":9,"teacher":"林芷瑩","room":"文LA 4003","classTime":["","","234","","","",""],"description":"《講授類》","tags":[],"english":false},{"url":"https://selcrs.nsysu.edu.tw/menu5/showoutline.asp?SYEAR=112&SEM=1&CrsDat=CL307A&Crsname=詞曲選及習作（一）","change":null,"changeDescription":null,"multipleCompulsory":true,"department":"中文系","id":"CL307A","grade":"3","class":"不分班","name":"詞曲選及習作（一）\nREADING IN TZ'U & CH'U POETRY(WITH EXERCISE)(I)","credit":"3","yearSemester":"期","compulsory":true,"restrict":30,"select":1,"selected":32,"remaining":-2,"teacher":"劉昭明","room":"文LA 4003","classTime":["","","","","234","",""],"description":"《講授類》","tags":[],"english":false},{"url":"https://selcrs.nsysu.edu.tw/menu5/showoutline.asp?SYEAR=112&SEM=1&CrsDat=CL330&Crsname=書法（一）","change":null,"changeDescription":null,"multipleCompulsory":false,"department":"中文系","id":"CL330","grade":"1","class":"不分班","name":"書法（一）\nCHINESE CALLIGRAPHY(I)","credit":"3","yearSemester":"期","compulsory":false,"restrict":50,"select":0,"selected":41,"remaining":9,"teacher":"楊雅惠","room":"文LA 5004","classTime":["","567","","","","",""],"description":"《講授類》","tags":[],"english":false},{"url":"https://selcrs.nsysu.edu.tw/menu5/showoutline.asp?SYEAR=112&SEM=1&CrsDat=CL335&Crsname=兩周青銅器銘文與「詩」、「書」文體之形成","change":null,"changeDescription":null,"multipleCompulsory":false,"department":"中文系","id":"CL335","grade":"4","class":"不分班","name":"兩周青銅器銘文與「詩」、「書」文體之形成\nBRONZE INSCRIPTIONS AND THE FROMATION OF THE SONGS AND DOCUMENTS AS LITERARY GENRES","credit":"3","yearSemester":"期","compulsory":false,"restrict":50,"select":0,"selected":4,"remaining":46,"teacher":"顧永光","room":"文LA 4004","classTime":["","234","","","","",""],"description":"《講授類》","tags":[],"english":false},{"url":"https://selcrs.nsysu.edu.tw/menu5/showoutline.asp?SYEAR=112&SEM=1&CrsDat=CL342&Crsname=聲韻學","change":"異動","changeDescription":"更換教室8/31","multipleCompulsory":false,"department":"中文系","id":"CL342","grade":"3","class":"不分班","name":"聲韻學\nCHINESE PHONOLOGY","credit":"3","yearSemester":"期","compulsory":true,"restrict":65,"select":0,"selected":63,"remaining":2,"teacher":"杜佳倫","room":"文LA 7006","classTime":["234","","","","","",""],"description":"《講授類》","tags":["中文創意跨域應用整合學程"],"english":false},{"url":"https://selcrs.nsysu.edu.tw/menu5/showoutline.asp?SYEAR=112&SEM=1&CrsDat=CL433&Crsname=臺灣古典文學概論","change":null,"changeDescription":null,"multipleCompulsory":false,"department":"中文系","id":"CL433","grade":"3","class":"不分班","name":"臺灣古典文學概論\nINTRODUCTION TO TAIWANESE CLASSICAL LITERATURE","credit":"3","yearSemester":"期","compulsory":false,"restrict":30,"select":0,"selected":17,"remaining":13,"teacher":"鍾志偉","room":"文LA 4003","classTime":["","234","","","","",""],"description":"《講授類》","tags":["臺灣研究學程","中文創意跨域應用整合學程"],"english":false},{"url":"https://selcrs.nsysu.edu.tw/menu5/showoutline.asp?SYEAR=112&SEM=1&CrsDat=CL439&Crsname=訓詁學","change":"異動","changeDescription":"更換教室及名額9/8","multipleCompulsory":false,"department":"中文系","id":"CL439","grade":"4","class":"不分班","name":"訓詁學\nEXEGETICS","credit":"2","yearSemester":"期","compulsory":true,"restrict":57,"select":0,"selected":55,"remaining":2,"teacher":"黃羽璿","room":"文LA 5004","classTime":["","","","56","","",""],"description":"《講授類》","tags":["中文創意跨域應用整合學程"],"english":false},{"url":"https://selcrs.nsysu.edu.tw/menu5/showoutline.asp?SYEAR=112&SEM=1&CrsDat=CL442&Crsname=地方敘事與數位遊戲設計","change":null,"changeDescription":null,"multipleCompulsory":false,"department":"中文系","id":"CL442","grade":"3","class":"不分班","name":"地方敘事與數位遊戲設計\nLOCAL NARRATIVE AND GAME PROGRAMMING","credit":"3","yearSemester":"期","compulsory":false,"restrict":50,"select":0,"selected":14,"remaining":36,"teacher":"杜佳倫","room":"文LA 5004","classTime":["567","","","","","",""],"description":"《講授類》","tags":["中文創意跨域應用整合學程"],"english":false},{"url":"https://selcrs.nsysu.edu.tw/menu5/showoutline.asp?SYEAR=112&SEM=1&CrsDat=CL453&Crsname=粵語文學導讀暨粵語入門","change":null,"changeDescription":null,"multipleCompulsory":false,"department":"中文系","id":"CL453","grade":"3","class":"不分班","name":"粵語文學導讀暨粵語入門\nREADINGS IN CANTONESE LITERATURE TOGETHER WITH AN INTRODUCTION TO CANTONESE","credit":"3","yearSemester":"期","compulsory":false,"restrict":50,"select":1,"selected":24,"remaining":26,"teacher":"顧永光","room":"文LA 4003","classTime":["","","567","","","",""],"description":"《講授類》","tags":[],"english":false},{"url":"https://selcrs.nsysu.edu.tw/menu5/showoutline.asp?SYEAR=112&SEM=1&CrsDat=CL454&Crsname=青聽文學","change":null,"changeDescription":null,"multipleCompulsory":false,"department":"中文系","id":"CL454","grade":"2","class":"不分班","name":"青聽文學\nYOUTHFUL LITERARY ENGAGEMENT: FROM TEXT TO WORLD","credit":"3","yearSemester":"期","compulsory":false,"restrict":30,"select":0,"selected":16,"remaining":14,"teacher":"杜佳倫,林芷瑩,賴佩暄","room":"文LA 4003","classTime":["","567","","","","",""],"description":"《講授類》","tags":["中文創意跨域應用整合學程"],"english":false},{"url":"https://selcrs.nsysu.edu.tw/menu5/showoutline.asp?SYEAR=112&SEM=1&CrsDat=CL455&Crsname=為你寫一首歌仔—戲曲創作與生命故事（一）","change":null,"changeDescription":null,"multipleCompulsory":false,"department":"中文系","id":"CL455","grade":"4","class":"不分班","name":"為你寫一首歌仔—戲曲創作與生命故事（一）\nINTERVIEWING AN ELDER AND WRITING A KOA-á  (I)","credit":"3","yearSemester":"期","compulsory":false,"restrict":30,"select":0,"selected":6,"remaining":24,"teacher":"林芷瑩","room":"文LA 4004","classTime":["","","567","","","",""],"description":"《講授類》","tags":["台灣閩南語文書寫應用與創作微學程"],"english":false},{"url":"https://selcrs.nsysu.edu.tw/menu5/showoutline.asp?SYEAR=112&SEM=1&CrsDat=DFLL101&Crsname=英文閱讀","change":"異動","changeDescription":"更換教室9/13","multipleCompulsory":false,"department":"外文系","id":"DFLL101","grade":"1","class":"不分班","name":"英文閱讀\nENGLISH READING","credit":"3","yearSemester":"期","compulsory":true,"restrict":50,"select":1,"selected":38,"remaining":12,"teacher":"洪敏秀","room":"文LA 1002","classTime":["","567","","","","",""],"description":"《講授類》\n『本課程之限修，於加退選2階段開放選修』。限本系生修習","tags":[],"english":true},{"url":"https://selcrs.nsysu.edu.tw/menu5/showoutline.asp?SYEAR=112&SEM=1&CrsDat=DFLL103&Crsname=英語聽力一（一）","change":null,"changeDescription":null,"multipleCompulsory":false,"department":"外文系","id":"DFLL103","grade":"1","class":"不分班","name":"英語聽力一（一）\nENGLISH LISTENING PRACTICE I(I)","credit":"1","yearSemester":"期","compulsory":true,"restrict":50,"select":0,"selected":36,"remaining":14,"teacher":"洪敏秀","room":"文LA 2001","classTime":["","","","","234","",""],"description":"《講授類》\n『本課程之限修，於加退選2階段開放選修』。限本系生修習","tags":[],"english":true},{"url":"https://selcrs.nsysu.edu.tw/menu5/showoutline.asp?SYEAR=112&SEM=1&CrsDat=DFLL105&Crsname=英語口語訓練一（一）","change":null,"changeDescription":null,"multipleCompulsory":true,"department":"外文系","id":"DFLL105","grade":"1","class":"不分班","name":"英語口語訓練一（一）\nENGLISH ORAL TRAINING I(I)","credit":"2","yearSemester":"期","compulsory":true,"restrict":16,"select":0,"selected":18,"remaining":-2,"teacher":"楊郁芬","room":"文LA 3002","classTime":["567","","","","","",""],"description":"《講授類》\n『本課程之限修，於加退選2階段開放選修』。限本系學生修習，大一新生統一配課","tags":[],"english":true},{"url":"https://selcrs.nsysu.edu.tw/menu5/showoutline.asp?SYEAR=112&SEM=1&CrsDat=DFLL105A&Crsname=英語口語訓練一（一）","change":"異動","changeDescription":"確認教師7/18","multipleCompulsory":true,"department":"外文系","id":"DFLL105A","grade":"1","class":"不分班","name":"英語口語訓練一（一）\nENGLISH ORAL TRAINING I(I)","credit":"2","yearSemester":"期","compulsory":true,"restrict":16,"select":0,"selected":15,"remaining":1,"teacher":"林毓凱","room":"文LA 3003","classTime":["567","","","","","",""],"description":"《講授類》\n『本課程之限修，於加退選2階段開放選修』。限本系生修習。大一新生統一配課","tags":[],"english":true},{"url":"https://selcrs.nsysu.edu.tw/menu5/showoutline.asp?SYEAR=112&SEM=1&CrsDat=DFLL105B&Crsname=英語口語訓練一（一）","change":null,"changeDescription":null,"multipleCompulsory":true,"department":"外文系","id":"DFLL105B","grade":"1","class":"不分班","name":"英語口語訓練一（一）\nENGLISH ORAL TRAINING I(I)","credit":"2","yearSemester":"期","compulsory":true,"restrict":16,"select":0,"selected":15,"remaining":1,"teacher":"黃舒屏","room":"文LA 3004","classTime":["567","","","","","",""],"description":"《講授類》\n『本課程之限修，於加退選2階段開放選修』。限本系生修習。大一新生統一配課","tags":[],"english":true},{"url":"https://selcrs.nsysu.edu.tw/menu5/showoutline.asp?SYEAR=112&SEM=1&CrsDat=DFLL107&Crsname=英文寫作一（一）","change":null,"changeDescription":null,"multipleCompulsory":true,"department":"外文系","id":"DFLL107","grade":"1","class":"不分班","name":"英文寫作一（一）\nENGLISH WRITING I(I)","credit":"2","yearSemester":"期","compulsory":true,"restrict":16,"select":0,"selected":18,"remaining":-2,"teacher":"陳福仁","room":"文LA 3002","classTime":["","","234","","","",""],"description":"《講授類》\n『本課程之限修，於加退選2階段開放選修』。限本系生修習。大一新生統一配課","tags":[],"english":false},{"url":"https://selcrs.nsysu.edu.tw/menu5/showoutline.asp?SYEAR=112&SEM=1&CrsDat=DFLL107A&Crsname=英文寫作一（一）","change":null,"changeDescription":null,"multipleCompulsory":true,"department":"外文系","id":"DFLL107A","grade":"1","class":"不分班","name":"英文寫作一（一）\nENGLISH WRITING I(I)","credit":"2","yearSemester":"期","compulsory":true,"restrict":16,"select":0,"selected":15,"remaining":1,"teacher":"楊郁芬","room":"文LA 3003","classTime":["","","234","","","",""],"description":"《講授類》\n『本課程之限修，於加退選2階段開放選修』。限本系生修習。大一新生統一配課","tags":[],"english":true}]