[{"url":"https://selcrs.nsysu.edu.tw/menu5/showoutline.asp?SYEAR=112&SEM=1&CrsDat=CL505A&Crsname=專題研究","change":null,"changeDescription":null,"multipleCompulsory":false,"department":"中文碩","id":"CL505A","grade":"0","class":"不分班","name":"專題研究\nINDEPENDENT STUDIES","credit":"1","yearSemester":"期","compulsory":false,"restrict":50,"select":0,"selected":1,"remaining":49,"teacher":"楊雅惠","room":"文LA 6009","classTime":["","2","","","","",""],"description":"《獨立研究》\n限二年級以上且已確定指導教授之碩博士生修習","tags":[],"english":false},{"url":"https://selcrs.nsysu.edu.tw/menu5/showoutline.asp?SYEAR=112&SEM=1&CrsDat=CL505B&Crsname=專題研究","change":null,"changeDescription":null,"multipleCompulsory":false,"department":"中文碩","id":"CL505B","grade":"0","class":"不分班","name":"專題研究\nINDEPENDENT STUDIES","credit":"1","yearSemester":"期","compulsory":false,"restrict":50,"select":0,"selected":0,"remaining":50,"teacher":"紀志昌","room":"文LA 6046","classTime":["","","","","5","",""],"description":"《獨立研究》\n限二年級以上且已確定指導教授之碩博士生修習","tags":[],"english":false},{"url":"https://selcrs.nsysu.edu.tw/menu5/showoutline.asp?SYEAR=112&SEM=1&CrsDat=CL513&Crsname=現代小說與理論（一）","change":null,"changeDescription":null,"multipleCompulsory":false,"department":"中文碩","id":"CL513","grade":"0","class":"不分班","name":"現代小說與理論（一）\nMODERN CHINESE FICTIONS AND THEORY(I)","credit":"2","yearSemester":"期","compulsory":false,"restrict":50,"select":0,"selected":16,"remaining":34,"teacher":"賴佩暄","room":"文LA 4013","classTime":["","","","34","","",""],"description":"《講授類》","tags":[],"english":false},{"url":"https://selcrs.nsysu.edu.tw/menu5/showoutline.asp?SYEAR=112&SEM=1&CrsDat=CL517&Crsname=中國書法美學","change":null,"changeDescription":null,"multipleCompulsory":false,"department":"中文碩","id":"CL517","grade":"0","class":"不分班","name":"中國書法美學\nTHE AESTHETICS OF CHINESE CALLIGRAPHY","credit":"3","yearSemester":"期","compulsory":false,"restrict":50,"select":0,"selected":18,"remaining":32,"teacher":"陳秋宏","room":"文LA 5004","classTime":["","","234","","","",""],"description":"《講授類》","tags":["跨文化人文思潮與美學微學程"],"english":false},{"url":"https://selcrs.nsysu.edu.tw/menu5/showoutline.asp?SYEAR=112&SEM=1&CrsDat=CL525&Crsname=詩經與抒情傳統","change":null,"changeDescription":null,"multipleCompulsory":false,"department":"中文碩","id":"CL525","grade":"0","class":"不分班","name":"詩經與抒情傳統\nSHIH CHING（BOOK OF ODES）AND LYRIC TRADITION","credit":"2","yearSemester":"期","compulsory":false,"restrict":50,"select":0,"selected":15,"remaining":35,"teacher":"楊雅惠","room":"文LA 5004","classTime":["","34","","","","",""],"description":"《講授類》\n碩博合開","tags":[],"english":false},{"url":"https://selcrs.nsysu.edu.tw/menu5/showoutline.asp?SYEAR=112&SEM=1&CrsDat=CL606&Crsname=民俗誌文獻學（一）","change":"新增","changeDescription":"8/9","multipleCompulsory":false,"department":"中文碩","id":"CL606","grade":"0","class":"不分班","name":"民俗誌文獻學（一）\nSTUDIES IN CHRONICLES OF CULTURE AND INFORMATION(I)","credit":"3","yearSemester":"期","compulsory":false,"restrict":50,"select":0,"selected":8,"remaining":42,"teacher":"楊濟襄","room":"文LA 4012","classTime":["678","","","","","",""],"description":"《講授類》","tags":[],"english":false},{"url":"https://selcrs.nsysu.edu.tw/menu5/showoutline.asp?SYEAR=112&SEM=1&CrsDat=CL608&Crsname=佛學思想","change":null,"changeDescription":null,"multipleCompulsory":false,"department":"中文碩","id":"CL608","grade":"0","class":"不分班","name":"佛學思想\nSTUDIES IN BUDDHIST THOUGHTS","credit":"3","yearSemester":"期","compulsory":false,"restrict":50,"select":1,"selected":8,"remaining":42,"teacher":"吳孟謙","room":"文LA 4013","classTime":["234","","","","","",""],"description":"《講授類》","tags":[],"english":false},{"url":"https://selcrs.nsysu.edu.tw/menu5/showoutline.asp?SYEAR=112&SEM=1&CrsDat=DFLL501&Crsname=學術寫作與書目學","change":null,"changeDescription":null,"multipleCompulsory":true,"department":"外文碩","id":"DFLL501","grade":"1","class":"不分班","name":"學術寫作與書目學\nACADEMIC WRITING AND BIBLIOGRAPHY","credit":"3","yearSemester":"期","compulsory":true,"restrict":50,"select":0,"selected":11,"remaining":39,"teacher":"黃心雅","room":"文LA 3018","classTime":["","","567","","","",""],"description":"《講授類》\n碩士班甲組","tags":[],"english":true},{"url":"https://selcrs.nsysu.edu.tw/menu5/showoutline.asp?SYEAR=112&SEM=1&CrsDat=DFLL504&Crsname=研究方法與學術寫作","change":null,"changeDescription":null,"multipleCompulsory":true,"department":"外文碩","id":"DFLL504","grade":"1","class":"不分班","name":"研究方法與學術寫作\nRESEARCH METHODS AND ACADEMIC WRITING","credit":"3","yearSemester":"期","compulsory":true,"restrict":50,"select":0,"selected":10,"remaining":40,"teacher":"徐淑瑛","room":"文LA 3017","classTime":["234","","","","","",""],"description":"《講授類》\n碩士班乙組","tags":[],"english":false},{"url":"https://selcrs.nsysu.edu.tw/menu5/showoutline.asp?SYEAR=112&SEM=1&CrsDat=DFLL621&Crsname=二十世紀美國戲劇","change":null,"changeDescription":null,"multipleCompulsory":false,"department":"外文碩","id":"DFLL621","grade":"0","class":"不分班","name":"二十世紀美國戲劇\n20TH CENTURY AMERICAN DRAMA","credit":"3","yearSemester":"期","compulsory":false,"restrict":50,"select":0,"selected":12,"remaining":38,"teacher":"范澤凱","room":"文LA 3018","classTime":["567","","","","","",""],"description":"《講授類》","tags":[],"english":true},{"url":"https://selcrs.nsysu.edu.tw/menu5/showoutline.asp?SYEAR=112&SEM=1&CrsDat=DFLL628&Crsname=當代北美原住民小說","change":null,"changeDescription":null,"multipleCompulsory":true,"department":"外文碩","id":"DFLL628","grade":"0","class":"不分班","name":"當代北美原住民小說\nCONTEMPORARY NORTH NATIVE AMERICAN NOVELS","credit":"3","yearSemester":"期","compulsory":false,"restrict":50,"select":0,"selected":3,"remaining":47,"teacher":"黃心雅","room":"文LA 3018","classTime":["","567","","","","",""],"description":"《講授類》","tags":[],"english":true},{"url":"https://selcrs.nsysu.edu.tw/menu5/showoutline.asp?SYEAR=112&SEM=1&CrsDat=DFLL651&Crsname=文類研究","change":"異動","changeDescription":"確認教師7/18","multipleCompulsory":false,"department":"外文碩","id":"DFLL651","grade":"0","class":"不分班","name":"文類研究\nGENRE STUDIES","credit":"3","yearSemester":"期","compulsory":false,"restrict":50,"select":0,"selected":10,"remaining":40,"teacher":"林毓凱","room":"文LA 3018","classTime":["","","","234","","",""],"description":"《講授類》","tags":[],"english":true},{"url":"https://selcrs.nsysu.edu.tw/menu5/showoutline.asp?SYEAR=112&SEM=1&CrsDat=DFLL666&Crsname=外語教學與科技：理論與實踐","change":"異動","changeDescription":"更換教室9/13","multipleCompulsory":false,"department":"外文碩","id":"DFLL666","grade":"0","class":"不分班","name":"外語教學與科技：理論與實踐\nFOREIGN LANGUAGE INSTRUCTION AND TECHNOLOGY：THEORY & PRACTICE","credit":"3","yearSemester":"期","compulsory":false,"restrict":50,"select":0,"selected":15,"remaining":35,"teacher":"楊郁芬","room":"文LA 3003","classTime":["","567","","","","",""],"description":"《講授類》","tags":[],"english":true},{"url":"https://selcrs.nsysu.edu.tw/menu5/showoutline.asp?SYEAR=112&SEM=1&CrsDat=DFLL668&Crsname=跨文化溝通","change":"異動","changeDescription":"更換教室9/11","multipleCompulsory":false,"department":"外文碩","id":"DFLL668","grade":"0","class":"不分班","name":"跨文化溝通\nINTERCULTURAL COMMUNICATION","credit":"3","yearSemester":"期","compulsory":false,"restrict":50,"select":1,"selected":16,"remaining":34,"teacher":"黃舒屏","room":"文LA 3001","classTime":["","","567","","","",""],"description":"《講授類》","tags":[],"english":true},{"url":"https://selcrs.nsysu.edu.tw/menu5/showoutline.asp?SYEAR=112&SEM=1&CrsDat=DFLL670&Crsname=漢英比較句法","change":null,"changeDescription":null,"multipleCompulsory":false,"department":"外文碩","id":"DFLL670","grade":"0","class":"不分班","name":"漢英比較句法\nCOMPARATIVE SYNTAX OF CHINESE AND ENGLISH","credit":"3","yearSemester":"期","compulsory":false,"restrict":50,"select":0,"selected":15,"remaining":35,"teacher":"徐淑瑛","room":"文LA 3017","classTime":["","234","","","","",""],"description":"《講授類》","tags":[],"english":false},{"url":"https://selcrs.nsysu.edu.tw/menu5/showoutline.asp?SYEAR=112&SEM=1&CrsDat=DFLL680&Crsname=專題研究","change":null,"changeDescription":null,"multipleCompulsory":true,"department":"外文碩","id":"DFLL680","grade":"2","class":"不分班","name":"專題研究\nINDEPENDENT STUDIES","credit":"3","yearSemester":"期","compulsory":true,"restrict":50,"select":0,"selected":1,"remaining":49,"teacher":"徐淑瑛","room":"","classTime":["","","","567","","",""],"description":"《獨立研究》","tags":[],"english":false},{"url":"https://selcrs.nsysu.edu.tw/menu5/showoutline.asp?SYEAR=112&SEM=1&CrsDat=DFLL680A&Crsname=專題研究","change":null,"changeDescription":null,"multipleCompulsory":true,"department":"外文碩","id":"DFLL680A","grade":"2","class":"不分班","name":"專題研究\nINDEPENDENT STUDIES","credit":"3","yearSemester":"期","compulsory":true,"restrict":50,"select":0,"selected":1,"remaining":49,"teacher":"盧莉茹","room":"","classTime":["","234","","","","",""],"description":"《獨立研究》","tags":[],"english":false},{"url":"https://selcrs.nsysu.edu.tw/menu5/showoutline.asp?SYEAR=112&SEM=1&CrsDat=DFLL680B&Crsname=專題研究","change":null,"changeDescription":null,"multipleCompulsory":true,"department":"外文碩","id":"DFLL680B","grade":"2","class":"不分班","name":"專題研究\nINDEPENDENT STUDIES","credit":"3","yearSemester":"期","compulsory":true,"restrict":50,"select":0,"selected":1,"remaining":49,"teacher":"賴怡芃","room":"","classTime":["","","","567","","",""],"description":"《獨立研究》","tags":[],"english":false},{"url":"https://selcrs.nsysu.edu.tw/menu5/showoutline.asp?SYEAR=112&SEM=1&CrsDat=MUSI502&Crsname=音樂理論總論","change":null,"changeDescription":null,"multipleCompulsory":false,"department":"音樂碩","id":"MUSI502","grade":"0","class":"不分班","name":"音樂理論總論\nMUSIC THEORY REVIEW","credit":"3","yearSemester":"期","compulsory":false,"restrict":50,"select":0,"selected":8,"remaining":42,"teacher":"李思嫺","room":"文FA 6011","classTime":["234","","","","","",""],"description":"《講授類》","tags":[],"english":false},{"url":"https://selcrs.nsysu.edu.tw/menu5/showoutline.asp?SYEAR=112&SEM=1&CrsDat=MUSI505&Crsname=音樂研究導論","change":null,"changeDescription":null,"multipleCompulsory":false,"department":"音樂碩","id":"MUSI505","grade":"1","class":"不分班","name":"音樂研究導論\nINTRODUCTION TO MUSIC RESEARCH","credit":"2","yearSemester":"期","compulsory":true,"restrict":50,"select":0,"selected":15,"remaining":35,"teacher":"郭瓊嬌","room":"文FA 6011","classTime":["","","34","","","",""],"description":"《講授類》","tags":[],"english":false}]