[{"url":"https://selcrs.nsysu.edu.tw/menu5/showoutline.asp?SYEAR=113&SEM=1&CrsDat=SOC105&Crsname=社會學實習（一）","change":null,"changeDescription":null,"multipleCompulsory":false,"department":"社會系","id":"SOC105","grade":"1","class":"不分班","name":"社會學實習（一）\nSOCIOLOGY PRACTICE ( I )","credit":"1","yearSemester":"期","compulsory":true,"restrict":50,"select":0,"selected":46,"remaining":4,"teacher":"李宛儒","room":"三D,E(社SS 1003)(實驗)","classTime":["","","DE","","","",""],"description":"《實習類》\n本課程限選修本系《社會學（一）》之學生。","tags":[],"english":false},{"url":"https://selcrs.nsysu.edu.tw/menu5/showoutline.asp?SYEAR=113&SEM=1&CrsDat=SOC130&Crsname=閱讀與寫作","change":"異動","changeDescription":"確認教師8/7","multipleCompulsory":false,"department":"社會系","id":"SOC130","grade":"1","class":"不分班","name":"閱讀與寫作\nREADING AND WRITING","credit":"3","yearSemester":"期","compulsory":true,"restrict":50,"select":2,"selected":47,"remaining":3,"teacher":"楊又欣","room":"一6,7,8(社SS 1003)","classTime":["678","","","","","",""],"description":"《講授類》","tags":["中文創意跨域應用整合學程"],"english":false},{"url":"https://selcrs.nsysu.edu.tw/menu5/showoutline.asp?SYEAR=113&SEM=1&CrsDat=SOC202&Crsname=南方社會學","change":"異動","changeDescription":"更換教室9/9","multipleCompulsory":false,"department":"社會系","id":"SOC202","grade":"3","class":"不分班","name":"南方社會學\nSOUTHERN SOCIOLOGY","credit":"3","yearSemester":"期","compulsory":true,"restrict":50,"select":1,"selected":56,"remaining":-6,"teacher":"林傳凱,王梅香","room":"三2,3,4(社SS 2001)","classTime":["","","234","","","",""],"description":"《講授類》","tags":[],"english":false},{"url":"https://selcrs.nsysu.edu.tw/menu5/showoutline.asp?SYEAR=113&SEM=1&CrsDat=SOC204&Crsname=社會學質性研究方法實習（一）","change":"異動","changeDescription":"更換部份時間9/20","multipleCompulsory":false,"department":"社會系","id":"SOC204","grade":"2","class":"不分班","name":"社會學質性研究方法實習（一）\nQUALITATIVE RESEARCH METHODS IN SOCIOLOGY: PRACTICE (I)","credit":"1","yearSemester":"期","compulsory":true,"restrict":50,"select":0,"selected":44,"remaining":6,"teacher":"萬毓澤,趙恩潔,陳美華","room":"二A(社SS 1003)(實驗) 四9(社SS 1003)(實驗)","classTime":["","A","","9","","",""],"description":"《實習類》\n本課程限選修本系《社會學質性研究方法（一）》之學生。","tags":[],"english":false},{"url":"https://selcrs.nsysu.edu.tw/menu5/showoutline.asp?SYEAR=113&SEM=1&CrsDat=SOC212&Crsname=媒體與社會","change":"新增","changeDescription":"8/12","multipleCompulsory":false,"department":"社會系","id":"SOC212","grade":"2","class":"不分班","name":"媒體與社會\nMEDIA AND SOCIETY","credit":"3","yearSemester":"期","compulsory":false,"restrict":50,"select":0,"selected":23,"remaining":27,"teacher":"戴昀","room":"五6,7,8(社SS 4004-2)","classTime":["","","","","678","",""],"description":"《講授類》\n \n※英語授課","tags":["全球研究學分學程"],"english":false},{"url":"https://selcrs.nsysu.edu.tw/menu5/showoutline.asp?SYEAR=113&SEM=1&CrsDat=SOC240&Crsname=永續發展與社會創新","change":"異動","changeDescription":"更換時間8/13","multipleCompulsory":false,"department":"社會系","id":"SOC240","grade":"2","class":"不分班","name":"永續發展與社會創新\nSUSTAINABILITY AND SOCIAL INNOVATION","credit":"3","yearSemester":"期","compulsory":false,"restrict":50,"select":0,"selected":15,"remaining":35,"teacher":"邱花妹","room":"二6,7,8(社SS 4004-2)","classTime":["","678","","","","",""],"description":"《講授類》","tags":["公民參與微學程","環境教育學程","永續發展與社會創新微學程"],"english":false},{"url":"https://selcrs.nsysu.edu.tw/menu5/showoutline.asp?SYEAR=113&SEM=1&CrsDat=SOC257&Crsname=全球政治","change":"異動","changeDescription":"更換時間8/20","multipleCompulsory":false,"department":"社會系","id":"SOC257","grade":"2","class":"不分班","name":"全球政治\nGLOBAL POLITICS","credit":"3","yearSemester":"期","compulsory":false,"restrict":25,"select":1,"selected":18,"remaining":7,"teacher":"方志恒","room":"五6,7,8(社SS 4001)","classTime":["","","","","678","",""],"description":"《講授類》\n \n※英語授課","tags":["全球研究學分學程","國際素養微學程"],"english":false},{"url":"https://selcrs.nsysu.edu.tw/menu5/showoutline.asp?SYEAR=113&SEM=1&CrsDat=SOC258&Crsname=原民的環境、經濟與社會","change":null,"changeDescription":null,"multipleCompulsory":false,"department":"社會系","id":"SOC258","grade":"2","class":"不分班","name":"原民的環境、經濟與社會\nINDIGENOUS ENVIRONMENT, ECONOMY AND SOCIETY","credit":"3","yearSemester":"期","compulsory":false,"restrict":10,"select":0,"selected":6,"remaining":4,"teacher":"王宏仁,巴清雄","room":"","classTime":["123456789","123456789","1234567CD","123456789","123456789","123456789",""],"description":"《講授類》\n暑假密集式授課8/12-8/17，限有修課同學選修","tags":[],"english":true},{"url":"https://selcrs.nsysu.edu.tw/menu5/showoutline.asp?SYEAR=113&SEM=1&CrsDat=SOC259&Crsname=全球勞工權利與標準","change":"異動","changeDescription":"確認教師8/13","multipleCompulsory":false,"department":"社會系","id":"SOC259","grade":"2","class":"不分班","name":"全球勞工權利與標準\nLABOUR RIGHTS AND STANDARDS AROUND THE WORLD","credit":"1","yearSemester":"期","compulsory":false,"restrict":50,"select":0,"selected":4,"remaining":46,"teacher":"夏榮","room":"","classTime":["234","234","2345","2345","2345","",""],"description":"《講授類》\n暑假密集式授課8/26-8/30，限有修課同學選修","tags":[],"english":true},{"url":"https://selcrs.nsysu.edu.tw/menu5/showoutline.asp?SYEAR=113&SEM=1&CrsDat=SOC260&Crsname=臺灣族群史","change":null,"changeDescription":null,"multipleCompulsory":false,"department":"社會系","id":"SOC260","grade":"2","class":"不分班","name":"臺灣族群史\nTHE ETHNIC HISTORY OF TAIWAN","credit":"3","yearSemester":"期","compulsory":false,"restrict":50,"select":0,"selected":23,"remaining":27,"teacher":"葉高華","room":"一6,7,8(社SS 4004-2)","classTime":["678","","","","","",""],"description":"《講授類》","tags":[],"english":false},{"url":"https://selcrs.nsysu.edu.tw/menu5/showoutline.asp?SYEAR=113&SEM=1&CrsDat=SOC301&Crsname=社會學質性研究方法（一）","change":null,"changeDescription":null,"multipleCompulsory":false,"department":"社會系","id":"SOC301","grade":"2","class":"不分班","name":"社會學質性研究方法（一）\nQUALITATIVE RESEARCH METHODS IN SOCIOLOGY (I)","credit":"3","yearSemester":"期","compulsory":true,"restrict":50,"select":0,"selected":44,"remaining":6,"teacher":"萬毓澤,趙恩潔,陳美華","room":"二2,3,4(社SS 1003)","classTime":["","234","","","","",""],"description":"《講授類》\n點選本課請同時點選《社會學質性研究方法實習（一）》","tags":[],"english":false},{"url":"https://selcrs.nsysu.edu.tw/menu5/showoutline.asp?SYEAR=113&SEM=1&CrsDat=SOC301A&Crsname=社會調查與研究方法（一）","change":null,"changeDescription":null,"multipleCompulsory":true,"department":"社會系","id":"SOC301A","grade":"3","class":"不分班","name":"社會調查與研究方法（一）\nSOCIAL SURVEY AND RESEARCH METHODS ( I )","credit":"3","yearSemester":"期","compulsory":true,"restrict":50,"select":0,"selected":10,"remaining":40,"teacher":"萬毓澤","room":"一2,3,4(社SS 3004-2)","classTime":["234","","","","","",""],"description":"《講授類》\n限修過本系或跨院選修之社會學(一)(二)且及格","tags":["環境教育學程","臺灣研究學程","永續發展與社會創新微學程","社區文創微學程"],"english":false},{"url":"https://selcrs.nsysu.edu.tw/menu5/showoutline.asp?SYEAR=113&SEM=1&CrsDat=SOC301B&Crsname=社會調查與研究方法（一）","change":null,"changeDescription":null,"multipleCompulsory":true,"department":"社會系","id":"SOC301B","grade":"3","class":"不分班","name":"社會調查與研究方法（一）\nSOCIAL SURVEY AND RESEARCH METHODS ( I )","credit":"3","yearSemester":"期","compulsory":true,"restrict":50,"select":0,"selected":10,"remaining":40,"teacher":"陳美華","room":"一2,3,4(社SS 4004-2)","classTime":["234","","","","","",""],"description":"《講授類》\n限修過本系或跨院選修之社會學(一)(二)且及格","tags":["環境教育學程","臺灣研究學程","永續發展與社會創新微學程","社區文創微學程"],"english":false},{"url":"https://selcrs.nsysu.edu.tw/menu5/showoutline.asp?SYEAR=113&SEM=1&CrsDat=SOC301C&Crsname=社會調查與研究方法（一）","change":null,"changeDescription":null,"multipleCompulsory":true,"department":"社會系","id":"SOC301C","grade":"3","class":"不分班","name":"社會調查與研究方法（一）\nSOCIAL SURVEY AND RESEARCH METHODS ( I )","credit":"3","yearSemester":"期","compulsory":true,"restrict":50,"select":0,"selected":11,"remaining":39,"teacher":"趙恩潔","room":"一2,3,4(社SS 1003)","classTime":["234","","","","","",""],"description":"《講授類》\n限修過本系或跨院選修之社會學(一)(二)且及格","tags":["環境教育學程","臺灣研究學程","永續發展與社會創新微學程","社區文創微學程"],"english":false},{"url":"https://selcrs.nsysu.edu.tw/menu5/showoutline.asp?SYEAR=113&SEM=1&CrsDat=SOC301D&Crsname=社會調查與研究方法（一）","change":null,"changeDescription":null,"multipleCompulsory":true,"department":"社會系","id":"SOC301D","grade":"3","class":"不分班","name":"社會調查與研究方法（一）\nSOCIAL SURVEY AND RESEARCH METHODS ( I )","credit":"3","yearSemester":"期","compulsory":true,"restrict":50,"select":0,"selected":9,"remaining":41,"teacher":"邱花妹","room":"一2,3,4(社SS 3004-1)","classTime":["234","","","","","",""],"description":"《講授類》\n限修過本系或跨院選修之社會學(一)(二)且及格","tags":["環境教育學程","臺灣研究學程","永續發展與社會創新微學程","社區文創微學程"],"english":false},{"url":"https://selcrs.nsysu.edu.tw/menu5/showoutline.asp?SYEAR=113&SEM=1&CrsDat=SOC301E&Crsname=社會調查與研究方法（一）","change":null,"changeDescription":null,"multipleCompulsory":true,"department":"社會系","id":"SOC301E","grade":"3","class":"不分班","name":"社會調查與研究方法（一）\nSOCIAL SURVEY AND RESEARCH METHODS ( I )","credit":"3","yearSemester":"期","compulsory":true,"restrict":50,"select":0,"selected":10,"remaining":40,"teacher":"王梅香","room":"一2,3,4(社SS 3007)","classTime":["234","","","","","",""],"description":"《講授類》\n限修過本系或跨院選修之社會學(一)(二)且及格","tags":["環境教育學程","臺灣研究學程","永續發展與社會創新微學程","社區文創微學程"],"english":false},{"url":"https://selcrs.nsysu.edu.tw/menu5/showoutline.asp?SYEAR=113&SEM=1&CrsDat=SOC302&Crsname=社會理論（一）","change":null,"changeDescription":null,"multipleCompulsory":false,"department":"社會系","id":"SOC302","grade":"2","class":"不分班","name":"社會理論（一）\nSOCIAL THEORIES (I)","credit":"3","yearSemester":"期","compulsory":true,"restrict":50,"select":0,"selected":47,"remaining":3,"teacher":"林傳凱","room":"二6,7,8(社SS 1003)","classTime":["","678","","","","",""],"description":"《講授類》","tags":[],"english":false},{"url":"https://selcrs.nsysu.edu.tw/menu5/showoutline.asp?SYEAR=113&SEM=1&CrsDat=SOC333&Crsname=文化資產保存與創新","change":"新增","changeDescription":"8/22","multipleCompulsory":false,"department":"社會系","id":"SOC333","grade":"3","class":"不分班","name":"文化資產保存與創新\nCULTURAL HERITAGE PRESERVATION AND INNOVATION","credit":"3","yearSemester":"期","compulsory":false,"restrict":50,"select":0,"selected":7,"remaining":43,"teacher":"王梅香,林傳凱","room":"五1,5,B(社SS 1003)","classTime":["","","","","1B5","",""],"description":"《講授類》\n限有修過113-1學期「社區文創設計」課程的同學選修。","tags":[],"english":false},{"url":"https://selcrs.nsysu.edu.tw/menu5/showoutline.asp?SYEAR=113&SEM=1&CrsDat=SOC339&Crsname=社區文創設計","change":null,"changeDescription":null,"multipleCompulsory":false,"department":"社會系","id":"SOC339","grade":"3","class":"不分班","name":"社區文創設計\nCULTURAL AND CREATIVE DESIGN OF COMMUNITY","credit":"3","yearSemester":"期","compulsory":false,"restrict":50,"select":0,"selected":9,"remaining":41,"teacher":"王梅香,林傳凱","room":"","classTime":["123456789CD","123456789CD","1234567CDE","123456789CD","123456789CD","",""],"description":"《講授類》\n暑假密集式授課6/24-6/28，限有修課同學選修","tags":["環境教育學程","中文創意跨域應用整合學程","社區文創微學程"],"english":false},{"url":"https://selcrs.nsysu.edu.tw/menu5/showoutline.asp?SYEAR=113&SEM=1&CrsDat=SOC341&Crsname=台灣漢人社區民族誌","change":null,"changeDescription":null,"multipleCompulsory":false,"department":"社會系","id":"SOC341","grade":"3","class":"不分班","name":"台灣漢人社區民族誌\nETHNOGRAPHY OF TAIWAN HAN CHINESE COMMUNITY","credit":"3","yearSemester":"期","compulsory":false,"restrict":50,"select":0,"selected":33,"remaining":17,"teacher":"莊英章","room":"四6,7,8(社SS 4004-2)","classTime":["","","","678","","",""],"description":"《講授類》","tags":[],"english":false}]