[{"url":"https://selcrs.nsysu.edu.tw/menu5/showoutline.asp?SYEAR=112&SEM=2&CrsDat=IMST585&Crsname=人體解剖學","change":null,"changeDescription":null,"multipleCompulsory":false,"department":"醫科碩","id":"IMST585","grade":"0","class":"不分班","name":"人體解剖學\nHUMAN ANATOMY","credit":"3","yearSemester":"期","compulsory":false,"restrict":45,"select":0,"selected":5,"remaining":40,"teacher":"柯翠玲","room":"國IR 5002","classTime":["","234","","","","",""],"description":"《講授類》","tags":[],"english":false},{"url":"https://selcrs.nsysu.edu.tw/menu5/showoutline.asp?SYEAR=112&SEM=2&CrsDat=IMST602&Crsname=書報討論（四）","change":null,"changeDescription":null,"multipleCompulsory":false,"department":"醫科碩","id":"IMST602","grade":"2","class":"不分班","name":"書報討論（四）\nSEMINAR (IV)","credit":"1","yearSemester":"期","compulsory":true,"restrict":50,"select":0,"selected":16,"remaining":34,"teacher":"范秀芳","room":"國IR 5002","classTime":["","","7","","","",""],"description":"《研討類》","tags":[],"english":false},{"url":"https://selcrs.nsysu.edu.tw/menu5/showoutline.asp?SYEAR=112&SEM=2&CrsDat=IMST613&Crsname=智慧長照書報討論（二）","change":null,"changeDescription":null,"multipleCompulsory":false,"department":"醫科碩","id":"IMST613","grade":"1","class":"不分班","name":"智慧長照書報討論（二）\nSEMINAR IN LONG-TERM CARE (II)","credit":"1","yearSemester":"期","compulsory":true,"restrict":50,"select":0,"selected":9,"remaining":41,"teacher":"王怡誠","room":"國IR 5003","classTime":["","","5","","","",""],"description":"《研討類》","tags":[],"english":false},{"url":"https://selcrs.nsysu.edu.tw/menu5/showoutline.asp?SYEAR=112&SEM=2&CrsDat=IMST614&Crsname=智慧長照實務","change":null,"changeDescription":null,"multipleCompulsory":false,"department":"醫科碩","id":"IMST614","grade":"1","class":"不分班","name":"智慧長照實務\nPRACTICUM IN INTELLIGENT LONG-TERM CARE","credit":"3","yearSemester":"期","compulsory":true,"restrict":50,"select":0,"selected":7,"remaining":43,"teacher":"羅貽豪","room":"校外實習單位","classTime":["","","","","","234",""],"description":"《講授類》","tags":["智慧長照微學程"],"english":false},{"url":"https://selcrs.nsysu.edu.tw/menu5/showoutline.asp?SYEAR=112&SEM=2&CrsDat=IMST615&Crsname=醫用生理與大數據之健康照護應用","change":null,"changeDescription":null,"multipleCompulsory":false,"department":"醫科碩","id":"IMST615","grade":"0","class":"不分班","name":"醫用生理與大數據之健康照護應用\nMEDICAL PHYSIOLOGY AND BIG DATA IN HEALTHCARE APPLICATION","credit":"2","yearSemester":"期","compulsory":false,"restrict":50,"select":0,"selected":1,"remaining":49,"teacher":"呂春輝,黃中佑","room":"國IR 1006-1","classTime":["","","","","34","",""],"description":"《講授類》","tags":[],"english":false},{"url":"https://selcrs.nsysu.edu.tw/menu5/showoutline.asp?SYEAR=112&SEM=2&CrsDat=IBPS502&Crsname=書報討論（二）","change":null,"changeDescription":null,"multipleCompulsory":false,"department":"生技醫藥碩","id":"IBPS502","grade":"1","class":"不分班","name":"書報討論（二）\nSEMINAR（II）","credit":"1","yearSemester":"期","compulsory":true,"restrict":50,"select":0,"selected":9,"remaining":41,"teacher":"徐志文","room":"國IR 5004","classTime":["","","3","","","",""],"description":"《講授類》","tags":[],"english":false},{"url":"https://selcrs.nsysu.edu.tw/menu5/showoutline.asp?SYEAR=112&SEM=2&CrsDat=IBPS504&Crsname=生技醫藥研發與技術特論","change":"異動","changeDescription":"更換合授教師1/23","multipleCompulsory":false,"department":"生技醫藥碩","id":"IBPS504","grade":"1","class":"不分班","name":"生技醫藥研發與技術特論\nRESEARCH AND TECHNOLOGIES IN THE DEVELOPMENT OF BIOPHARMACEUTICALS","credit":"2","yearSemester":"期","compulsory":true,"restrict":50,"select":0,"selected":9,"remaining":41,"teacher":"孫羽佑,余靈珊,徐志文","room":"國IR 5001","classTime":["","","","","34","",""],"description":"《講授類》","tags":["天然藥物合成學程"],"english":false},{"url":"https://selcrs.nsysu.edu.tw/menu5/showoutline.asp?SYEAR=112&SEM=2&CrsDat=IBPS507&Crsname=生理調控與人類疾病","change":null,"changeDescription":null,"multipleCompulsory":false,"department":"生技醫藥碩","id":"IBPS507","grade":"0","class":"不分班","name":"生理調控與人類疾病\nBODY PROCESSES AND DISEASE PROGRESSION","credit":"3","yearSemester":"期","compulsory":false,"restrict":50,"select":0,"selected":3,"remaining":47,"teacher":"孫羽佑","room":"國IR 5004","classTime":["","","","234","","",""],"description":"《講授類》","tags":[],"english":false},{"url":"https://selcrs.nsysu.edu.tw/menu5/showoutline.asp?SYEAR=112&SEM=2&CrsDat=IBPS514&Crsname=癌症標靶治療學","change":null,"changeDescription":null,"multipleCompulsory":false,"department":"生技醫藥碩","id":"IBPS514","grade":"0","class":"不分班","name":"癌症標靶治療學\nTARGETED THERAPIES FOR MALIGNANT TUMORS","credit":"3","yearSemester":"期","compulsory":false,"restrict":50,"select":0,"selected":8,"remaining":42,"teacher":"徐志文","room":"國IR 5005","classTime":["","","","234","","",""],"description":"《講授類》","tags":[],"english":true},{"url":"https://selcrs.nsysu.edu.tw/menu5/showoutline.asp?SYEAR=112&SEM=2&CrsDat=IBPS517&Crsname=大分子藥物開發特論","change":null,"changeDescription":null,"multipleCompulsory":false,"department":"生技醫藥碩","id":"IBPS517","grade":"0","class":"不分班","name":"大分子藥物開發特論\nDEVELOPMENT OF MACROMOLECULAR THERAPEUTICS","credit":"3","yearSemester":"期","compulsory":false,"restrict":50,"select":0,"selected":5,"remaining":45,"teacher":"孫羽佑","room":"國IR 5005","classTime":["","678","","","","",""],"description":"《講授類》\n \n※英語授課","tags":["天然藥物合成學程"],"english":false}]