[{"url":"https://selcrs.nsysu.edu.tw/menu5/showoutline.asp?SYEAR=112&SEM=2&CrsDat=ICM646&Crsname=全球化媒體專題研究","change":null,"changeDescription":null,"multipleCompulsory":false,"department":"行銷傳播碩","id":"ICM646","grade":"0","class":"不分班","name":"全球化媒體專題研究\nINDEPENDENT STUDIES IN MEDIA GLOBALIZATION","credit":"3","yearSemester":"期","compulsory":false,"restrict":50,"select":5,"selected":1,"remaining":49,"teacher":"王紹蓉","room":"管CM 2032","classTime":["","","","","","CDE",""],"description":"《獨立研究》\n限行傳所學生選修","tags":[],"english":true},{"url":"https://selcrs.nsysu.edu.tw/menu5/showoutline.asp?SYEAR=112&SEM=2&CrsDat=ICM647&Crsname=資訊科技與社會專題研究","change":null,"changeDescription":null,"multipleCompulsory":false,"department":"行銷傳播碩","id":"ICM647","grade":"0","class":"不分班","name":"資訊科技與社會專題研究\nINDEPENDENT STUDIES IN INFORMATION TECHNOLOGY AND SOCIETY","credit":"3","yearSemester":"期","compulsory":false,"restrict":50,"select":0,"selected":0,"remaining":50,"teacher":"鄭安授","room":"管CM 2032","classTime":["234","","","","","",""],"description":"《獨立研究》\n限行傳所碩士班二年級以上學生選修","tags":[],"english":false},{"url":"https://selcrs.nsysu.edu.tw/menu5/showoutline.asp?SYEAR=112&SEM=2&CrsDat=ICM652&Crsname=進階傳播研究法","change":null,"changeDescription":null,"multipleCompulsory":false,"department":"行銷傳播碩","id":"ICM652","grade":"0","class":"不分班","name":"進階傳播研究法\nADVANCED RESEARCH METHODS FOR COMMUNICATIONS","credit":"3","yearSemester":"期","compulsory":false,"restrict":50,"select":0,"selected":18,"remaining":32,"teacher":"張榮華","room":"管CM 2029","classTime":["","","CDE","","","",""],"description":"《講授類》\n限已修畢量化研究方法或統計學者選修","tags":[],"english":false},{"url":"https://selcrs.nsysu.edu.tw/menu5/showoutline.asp?SYEAR=112&SEM=2&CrsDat=ICM653&Crsname=專題研究（一）","change":null,"changeDescription":null,"multipleCompulsory":false,"department":"行銷傳播碩","id":"ICM653","grade":"0","class":"不分班","name":"專題研究（一）\nINDEPENDENT STUDIES(I)","credit":"3","yearSemester":"期","compulsory":false,"restrict":50,"select":0,"selected":0,"remaining":50,"teacher":"待聘","room":"管CM 2032","classTime":["","","","","CDE","",""],"description":"《獨立研究》\n限行傳所碩士班二年級以上學生選修","tags":[],"english":false},{"url":"https://selcrs.nsysu.edu.tw/menu5/showoutline.asp?SYEAR=112&SEM=2&CrsDat=ICM654&Crsname=專題研究（二）","change":null,"changeDescription":null,"multipleCompulsory":false,"department":"行銷傳播碩","id":"ICM654","grade":"0","class":"不分班","name":"專題研究（二）\nINDEPENDENT STUDIES(II)","credit":"3","yearSemester":"期","compulsory":false,"restrict":50,"select":0,"selected":0,"remaining":50,"teacher":"待聘","room":"管CM 2032","classTime":["","","","","","234",""],"description":"《獨立研究》\n限行傳所碩士班二年級以上學生選修","tags":[],"english":false},{"url":"https://selcrs.nsysu.edu.tw/menu5/showoutline.asp?SYEAR=112&SEM=2&CrsDat=ICM655&Crsname=專題研究（三）","change":null,"changeDescription":null,"multipleCompulsory":false,"department":"行銷傳播碩","id":"ICM655","grade":"0","class":"不分班","name":"專題研究（三）\nINDEPENDENT STUDIES(III)","credit":"3","yearSemester":"期","compulsory":false,"restrict":50,"select":0,"selected":0,"remaining":50,"teacher":"待聘","room":"管CM 2032","classTime":["","","234","","","",""],"description":"《獨立研究》\n限行傳所碩士班二年級以上學生選修","tags":[],"english":false},{"url":"https://selcrs.nsysu.edu.tw/menu5/showoutline.asp?SYEAR=112&SEM=2&CrsDat=ICM661&Crsname=AI行銷專題研究","change":null,"changeDescription":null,"multipleCompulsory":false,"department":"行銷傳播碩","id":"ICM661","grade":"0","class":"不分班","name":"AI行銷專題研究\nINDEPENDENT STUDIES IN AI IN MARKETING","credit":"3","yearSemester":"期","compulsory":false,"restrict":50,"select":0,"selected":1,"remaining":49,"teacher":"李雅靖","room":"管CM 2029","classTime":["","","567","","","",""],"description":"《獨立研究》\n限行傳所碩士班二年級以上學生選修","tags":[],"english":false},{"url":"https://selcrs.nsysu.edu.tw/menu5/showoutline.asp?SYEAR=112&SEM=2&CrsDat=ICM662&Crsname=行銷管理專題研究","change":null,"changeDescription":null,"multipleCompulsory":false,"department":"行銷傳播碩","id":"ICM662","grade":"0","class":"不分班","name":"行銷管理專題研究\nINDEPENDENT STUDIES IN MARKETING MANAGEMENT","credit":"3","yearSemester":"期","compulsory":false,"restrict":50,"select":0,"selected":1,"remaining":49,"teacher":"張榮華","room":"管CM 2032","classTime":["","","567","","","",""],"description":"《獨立研究》\n限行傳所碩士班二年級以上學生選修","tags":[],"english":false},{"url":"https://selcrs.nsysu.edu.tw/menu5/showoutline.asp?SYEAR=112&SEM=2&CrsDat=CM505&Crsname=商業大數據分析資料案例","change":null,"changeDescription":null,"multipleCompulsory":false,"department":"管理學院(碩)","id":"CM505","grade":"0","class":"不分班","name":"商業大數據分析資料案例\nBUSINESS BIG DATA ANALYTICS CAPSTONE","credit":"3","yearSemester":"期","compulsory":false,"restrict":50,"select":3,"selected":25,"remaining":25,"teacher":"康藝晃,卓雍然","room":"管CM 4069","classTime":["","","","","567","",""],"description":"《講授類》\n商業數據分析與創新微學程/本課程須會使用基礎R語言，未有此能力者請勿修習","tags":["商業數據分析與創新微學程"],"english":false},{"url":"https://selcrs.nsysu.edu.tw/menu5/showoutline.asp?SYEAR=112&SEM=2&CrsDat=CM506&Crsname=金融服務與金融科技資料案例","change":null,"changeDescription":null,"multipleCompulsory":false,"department":"管理學院(碩)","id":"CM506","grade":"0","class":"不分班","name":"金融服務與金融科技資料案例\nFINANCIAL SERVICE AND FINANCIAL TECHNOLOGY CAPSTONE","credit":"3","yearSemester":"期","compulsory":false,"restrict":50,"select":0,"selected":10,"remaining":40,"teacher":"王昭文,卓雍然","room":"管CM 3035","classTime":["","","","","567","",""],"description":"《講授類》\n金融數據分析與創新微學程/本課程須會使用基礎R語言，未有此能力者請勿修習","tags":["金融數據分析與創新微學程"],"english":false}]