[{"url":"https://selcrs.nsysu.edu.tw/menu5/showoutline.asp?SYEAR=113&SEM=2&CrsDat=MATH727&Crsname=計算書報討論（二）","change":null,"changeDescription":null,"multipleCompulsory":true,"department":"應數博","id":"MATH727","grade":"1","class":"不分班","name":"計算書報討論（二）\nSEMINAR IN SCIENTIFIC COMPUTING(II)","credit":"1","yearSemester":"期","compulsory":true,"restrict":5,"select":0,"selected":0,"remaining":5,"teacher":"李宗錂","room":"四7(理SC 4011)","classTime":["","","","7","","",""],"description":"《講授類》","tags":[],"english":false},{"url":"https://selcrs.nsysu.edu.tw/menu5/showoutline.asp?SYEAR=113&SEM=2&CrsDat=MATH752&Crsname=數學書報討論（二）","change":null,"changeDescription":null,"multipleCompulsory":true,"department":"應數博","id":"MATH752","grade":"1","class":"不分班","name":"數學書報討論（二）\nSEMINAR IN MATHEMATICS(II)","credit":"1","yearSemester":"期","compulsory":true,"restrict":5,"select":0,"selected":0,"remaining":5,"teacher":"許柏翰","room":"四7(理SC 4013)","classTime":["","","","7","","",""],"description":"《講授類》","tags":[],"english":false},{"url":"https://selcrs.nsysu.edu.tw/menu5/showoutline.asp?SYEAR=113&SEM=2&CrsDat=MATH757&Crsname=算子理論及應用","change":"異動","changeDescription":"更換時間及教室1/3","multipleCompulsory":false,"department":"應數博","id":"MATH757","grade":"0","class":"不分班","name":"算子理論及應用\nOPERATOR THEORY AND APPLICATIONS","credit":"3","yearSemester":"期","compulsory":false,"restrict":5,"select":1,"selected":0,"remaining":5,"teacher":"黃毅青","room":"四5,6,7(理SC 4011-2)","classTime":["","","","567","","",""],"description":"《講授類》","tags":[],"english":true},{"url":"https://selcrs.nsysu.edu.tw/menu5/showoutline.asp?SYEAR=113&SEM=2&CrsDat=PPFS721&Crsname=書報討論（二）","change":null,"changeDescription":null,"multipleCompulsory":false,"department":"理學博","id":"PPFS721","grade":"1","class":"不分班","name":"書報討論（二）\nSEMINAR（II）","credit":"1","yearSemester":"期","compulsory":true,"restrict":50,"select":0,"selected":4,"remaining":46,"teacher":"楊崇鑫","room":"五4(理SC 0010)","classTime":["","","","","4","",""],"description":"《研討類》","tags":[],"english":true},{"url":"https://selcrs.nsysu.edu.tw/menu5/showoutline.asp?SYEAR=113&SEM=2&CrsDat=PPFS723&Crsname=專題研究（二）","change":null,"changeDescription":null,"multipleCompulsory":false,"department":"理學博","id":"PPFS723","grade":"2","class":"不分班","name":"專題研究（二）\nINDEPENDENT STUDIES（II）","credit":"3","yearSemester":"期","compulsory":true,"restrict":50,"select":2,"selected":2,"remaining":48,"teacher":"楊崇鑫","room":"一1(理SC 0010) 二1,2(理SC 0010)","classTime":["1","12","","","","",""],"description":"《獨立研究》","tags":[],"english":true},{"url":"https://selcrs.nsysu.edu.tw/menu5/showoutline.asp?SYEAR=113&SEM=2&CrsDat=PPFS725&Crsname=分子與雷射光譜","change":null,"changeDescription":null,"multipleCompulsory":false,"department":"理學博","id":"PPFS725","grade":"1","class":"不分班","name":"分子與雷射光譜\nMOLECULAR AND LASER SPECTROSCOPY","credit":"3","yearSemester":"期","compulsory":false,"restrict":50,"select":2,"selected":0,"remaining":50,"teacher":"楊崇鑫","room":"一2,3,4(理SC 0010)","classTime":["234","","","","","",""],"description":"《講授類》","tags":[],"english":true},{"url":"https://selcrs.nsysu.edu.tw/menu5/showoutline.asp?SYEAR=113&SEM=2&CrsDat=EE7100&Crsname=書報討論","change":null,"changeDescription":null,"multipleCompulsory":false,"department":"電機博","id":"EE7100","grade":"1","class":"不分班","name":"書報討論\nSEMINAR","credit":"1","yearSemester":"期","compulsory":true,"restrict":90,"select":1,"selected":6,"remaining":84,"teacher":"謝耀慶","room":"二6,7(工EC 6019)","classTime":["","67","","","","",""],"description":"《研討類》\n碩、博士班併班上課","tags":[],"english":false},{"url":"https://selcrs.nsysu.edu.tw/menu5/showoutline.asp?SYEAR=113&SEM=2&CrsDat=EE7701&Crsname=高等磁共振影像技術","change":null,"changeDescription":null,"multipleCompulsory":false,"department":"電機博","id":"EE7701","grade":"0","class":"不分班","name":"高等磁共振影像技術\nADVANCED TECHNIQUES OF MAGNETIC RESONANCE IMAGING","credit":"3","yearSemester":"期","compulsory":false,"restrict":50,"select":5,"selected":0,"remaining":50,"teacher":"莊子肇,吳珮歆,程正傑","room":"二2,3,4(工EC 2018)","classTime":["","234","","","","",""],"description":"《講授類》","tags":[],"english":false},{"url":"https://selcrs.nsysu.edu.tw/menu5/showoutline.asp?SYEAR=113&SEM=2&CrsDat=MEME701&Crsname=書報討論","change":null,"changeDescription":null,"multipleCompulsory":false,"department":"機電博","id":"MEME701","grade":"1","class":"不分班","name":"書報討論\nSEMINAR","credit":"1","yearSemester":"期","compulsory":true,"restrict":100,"select":0,"selected":7,"remaining":93,"teacher":"王郁仁","room":"四6,7(工EN 2028)","classTime":["","","","67","","",""],"description":"《演講/參訪》\n碩、博士班併班上課","tags":[],"english":false},{"url":"https://selcrs.nsysu.edu.tw/menu5/showoutline.asp?SYEAR=113&SEM=2&CrsDat=ENVE721&Crsname=書報討論","change":null,"changeDescription":null,"multipleCompulsory":false,"department":"環工博","id":"ENVE721","grade":"1","class":"不分班","name":"書報討論\nSEMINAR","credit":"1","yearSemester":"期","compulsory":true,"restrict":50,"select":0,"selected":3,"remaining":47,"teacher":"陳威翔","room":"三6,7(工EV 4024)","classTime":["","","67","","","",""],"description":"《演講/參訪》","tags":[],"english":false},{"url":"https://selcrs.nsysu.edu.tw/menu5/showoutline.asp?SYEAR=113&SEM=2&CrsDat=ENVE721A&Crsname=書報討論","change":null,"changeDescription":null,"multipleCompulsory":false,"department":"環工博","id":"ENVE721A","grade":"2","class":"不分班","name":"書報討論\nSEMINAR","credit":"1","yearSemester":"期","compulsory":true,"restrict":50,"select":0,"selected":7,"remaining":43,"teacher":"陳威翔","room":"三6,7(工EV 4024)","classTime":["","","67","","","",""],"description":"《演講/參訪》","tags":[],"english":false},{"url":"https://selcrs.nsysu.edu.tw/menu5/showoutline.asp?SYEAR=113&SEM=2&CrsDat=ENVE721B&Crsname=書報討論","change":null,"changeDescription":null,"multipleCompulsory":false,"department":"環工博","id":"ENVE721B","grade":"3","class":"不分班","name":"書報討論\nSEMINAR","credit":"1","yearSemester":"期","compulsory":true,"restrict":50,"select":0,"selected":8,"remaining":42,"teacher":"陳威翔","room":"三6,7(工EV 4024)","classTime":["","","67","","","",""],"description":"《演講/參訪》","tags":[],"english":false},{"url":"https://selcrs.nsysu.edu.tw/menu5/showoutline.asp?SYEAR=113&SEM=2&CrsDat=ENVE737&Crsname=事業廢水工程設計","change":null,"changeDescription":null,"multipleCompulsory":false,"department":"環工博","id":"ENVE737","grade":"0","class":"不分班","name":"事業廢水工程設計\nWASTEWATER TREATMENT ENGINEERING","credit":"3","yearSemester":"期","compulsory":false,"restrict":50,"select":1,"selected":0,"remaining":50,"teacher":"張耿崚","room":"五2,3,4(工EC 1004)","classTime":["","","","","234","",""],"description":"《講授類》","tags":["環境教育學程"],"english":false},{"url":"https://selcrs.nsysu.edu.tw/menu5/showoutline.asp?SYEAR=113&SEM=2&CrsDat=ENVE741&Crsname=氣膠學","change":null,"changeDescription":null,"multipleCompulsory":false,"department":"環工博","id":"ENVE741","grade":"0","class":"不分班","name":"氣膠學\nAEROSOL TECHNOLOGY","credit":"3","yearSemester":"期","compulsory":false,"restrict":50,"select":3,"selected":0,"remaining":50,"teacher":"陳則綸","room":"二6,7,8(工EC 2005)","classTime":["","678","","","","",""],"description":"《講授類》\n \n※英語授課","tags":["環境科技與管理學程"],"english":false},{"url":"https://selcrs.nsysu.edu.tw/menu5/showoutline.asp?SYEAR=113&SEM=2&CrsDat=ENVE776&Crsname=環境宿命與風險評估","change":null,"changeDescription":null,"multipleCompulsory":false,"department":"環工博","id":"ENVE776","grade":"0","class":"不分班","name":"環境宿命與風險評估\nENVIRONMENTAL FATE AND RISK ASSESSMENT","credit":"3","yearSemester":"期","compulsory":false,"restrict":50,"select":4,"selected":0,"remaining":50,"teacher":"陳威翔","room":"三C,D,E(工EC 1004)","classTime":["","","CDE","","","",""],"description":"《講授類》\n \n※英語授課","tags":["氣膠、大氣與海洋微學程"],"english":false},{"url":"https://selcrs.nsysu.edu.tw/menu5/showoutline.asp?SYEAR=113&SEM=2&CrsDat=ENVE785&Crsname=高等水化學","change":null,"changeDescription":null,"multipleCompulsory":false,"department":"環工博","id":"ENVE785","grade":"0","class":"不分班","name":"高等水化學\nADVANCED WATER CHEMISTRY","credit":"3","yearSemester":"期","compulsory":false,"restrict":50,"select":3,"selected":0,"remaining":50,"teacher":"施育仁","room":"四2,3,4(工EC 1004)","classTime":["","","","234","","",""],"description":"《講授類》","tags":[],"english":false},{"url":"https://selcrs.nsysu.edu.tw/menu5/showoutline.asp?SYEAR=113&SEM=2&CrsDat=ENVE791&Crsname=英文論文寫作","change":null,"changeDescription":null,"multipleCompulsory":false,"department":"環工博","id":"ENVE791","grade":"0","class":"不分班","name":"英文論文寫作\nTECHNICAL WRITING IN EHGLISH","credit":"2","yearSemester":"期","compulsory":false,"restrict":50,"select":47,"selected":0,"remaining":50,"teacher":"施育仁","room":"二C,D(工EV 4024)","classTime":["","CD","","","","",""],"description":"《講授類》","tags":[],"english":true},{"url":"https://selcrs.nsysu.edu.tw/menu5/showoutline.asp?SYEAR=113&SEM=2&CrsDat=CSE707&Crsname=書報討論（二）","change":null,"changeDescription":null,"multipleCompulsory":false,"department":"資工博","id":"CSE707","grade":"1","class":"不分班","name":"書報討論（二）\nSEMINAR II","credit":"1","yearSemester":"期","compulsory":true,"restrict":10,"select":0,"selected":5,"remaining":5,"teacher":"王友群","room":"五6(工EC 2011)","classTime":["","","","","6","",""],"description":"《演講/參訪》\n限本系碩/博士生修習","tags":[],"english":false},{"url":"https://selcrs.nsysu.edu.tw/menu5/showoutline.asp?SYEAR=113&SEM=2&CrsDat=ICE701&Crsname=書報討論","change":null,"changeDescription":null,"multipleCompulsory":false,"department":"通訊博","id":"ICE701","grade":"1","class":"不分班","name":"書報討論\nSEMINAR","credit":"1","yearSemester":"期","compulsory":true,"restrict":50,"select":0,"selected":4,"remaining":46,"teacher":"曾凡碩","room":"二6,7(工EC 2002)","classTime":["","67","","","","",""],"description":"《演講/參訪》\n與ICE501、ICE501A併班上課","tags":[],"english":false},{"url":"https://selcrs.nsysu.edu.tw/menu5/showoutline.asp?SYEAR=113&SEM=2&CrsDat=EO7146&Crsname=書報討論（二）","change":null,"changeDescription":null,"multipleCompulsory":false,"department":"光電博","id":"EO7146","grade":"1","class":"不分班","name":"書報討論（二）\nSEMINAR(II)","credit":"1","yearSemester":"期","compulsory":true,"restrict":50,"select":1,"selected":4,"remaining":46,"teacher":"林煒淳","room":"一6,7,8(國IR 3003)","classTime":["678","","","","","",""],"description":"《講授類》","tags":[],"english":false}]